bokger/Database.py
bokger/Logger.py
bokger/OpTable.py
bokger/__init__.py
bokger/_at_enter.py
bokger/_at_exit.py
bokger/_dec_io_and_time.py
bokger/_version.py
bokger/dec.py
bokger/models/CopyToClipboard.js
bokger/models/CopyToClipboardButton.py
bokger/models/DownloadCsv.js
bokger/models/DownloadCsvButton.py
bokger/models/DownloadFile.js
bokger/models/DownloadFileButton.py
bokger/models/__init__.py
bokger/utilities/Caller.py
bokger/utilities/TimeStamp.py
bokger/utilities/__init__.py
tests/test_dec.py
tests/test_exception.py
tests/test_init.py
tests/test_log.py
tests/test_source.py
bokger-0.7.3.dist-info/METADATA
bokger-0.7.3.dist-info/WHEEL
bokger-0.7.3.dist-info/top_level.txt
bokger-0.7.3.dist-info/RECORD
